odoo/addons/sale_expense_unlink/LICENSE
odoo/addons/sale_expense_unlink/README.rst
odoo/addons/sale_expense_unlink/__init__.py
odoo/addons/sale_expense_unlink/__manifest__.py
odoo/addons/sale_expense_unlink/images/screen.png
odoo/addons/sale_expense_unlink/models/__init__.py
odoo/addons/sale_expense_unlink/models/hr_expense_sheet.py
odoo/addons/sale_expense_unlink/models/sale_order_line.py
odoo/addons/sale_expense_unlink/static/description/icon.png
odoo/addons/sale_expense_unlink/static/description/index.html
odoo/addons/sale_expense_unlink/tests/TEST_INSTRUCTIONS.rst
odoo_addon_sale_expense_unlink-16.0.1.0.0.dist-info/METADATA
odoo_addon_sale_expense_unlink-16.0.1.0.0.dist-info/WHEEL
odoo_addon_sale_expense_unlink-16.0.1.0.0.dist-info/top_level.txt
odoo_addon_sale_expense_unlink-16.0.1.0.0.dist-info/RECORD
